sidewalkdemo/__init__.py
sidewalkdemo-0.2.dist-info/LICENSE.txt
sidewalkdemo-0.2.dist-info/METADATA
sidewalkdemo-0.2.dist-info/WHEEL
sidewalkdemo-0.2.dist-info/top_level.txt
sidewalkdemo-0.2.dist-info/RECORD
