Metadata-Version: 2.1
Name: sidewalkdemo
Version: 0.2
Summary: This is an implementation of sidewalk environment for reinforcement learning
Author: Zhanzhi Jiang
Author-email: hnzjzz@gmail.com
Classifier: Programming Language :: Python :: 3
Classifier: License :: OSI Approved :: MIT License
Classifier: Operating System :: OS Independent
License-File: LICENSE.txt
